epydemics/__init__.py
epydemics/epydemics.py
epydemics/analysis/__init__.py
epydemics/analysis/evaluation.py
epydemics/analysis/formatting.py
epydemics/analysis/reporting.py
epydemics/analysis/seasonality.py
epydemics/analysis/visualization.py
epydemics/core/__init__.py
epydemics/core/config.py
epydemics/core/constants.py
epydemics/core/exceptions.py
epydemics/data/__init__.py
epydemics/data/container.py
epydemics/data/features.py
epydemics/data/frequency_handlers.py
epydemics/data/preprocessing.py
epydemics/data/validation.py
epydemics/models/__init__.py
epydemics/models/base.py
epydemics/models/simulation.py
epydemics/models/sird.py
epydemics/models/var_forecasting.py
epydemics/models/forecasting/__init__.py
epydemics/models/forecasting/arima.py
epydemics/models/forecasting/base.py
epydemics/models/forecasting/lstm.py
epydemics/models/forecasting/orchestrator.py
epydemics/models/forecasting/prophet.py
epydemics/models/forecasting/registry.py
epydemics/models/forecasting/var.py
epydemics/utils/__init__.py
epydemics/utils/transformations.py
epydemics-0.11.2.dist-info/licenses/LICENSE
epydemics-0.11.2.dist-info/METADATA
epydemics-0.11.2.dist-info/WHEEL
epydemics-0.11.2.dist-info/top_level.txt
epydemics-0.11.2.dist-info/RECORD
