Metadata-Version: 2.4
Name: epydemics
Version: 0.11.2
Summary: Advanced epidemiological modeling and forecasting using discrete SIRD/SIRDV models with time series analysis
Author-email: Juliho David Castillo Colmenares <juliho.colmenares@gmail.com>
Maintainer-email: Juliho David Castillo Colmenares <juliho.colmenares@gmail.com>
License-Expression: MIT
Project-URL: Homepage, https://github.com/julihocc/epydemics
Project-URL: Documentation, https://github.com/julihocc/epydemics#readme
Project-URL: Repository, https://github.com/julihocc/epydemics.git
Project-URL: Bug Tracker, https://github.com/julihocc/epydemics/issues
Project-URL: Changelog, https://github.com/julihocc/epydemics/blob/main/CHANGELOG.md
Keywords: epidemiology,modeling,forecasting,sird,time-series,var,monte-carlo,covid,pandemic
Classifier: Development Status :: 4 - Beta
Classifier: Intended Audience :: Science/Research
Classifier: Intended Audience :: Healthcare Industry
Classifier: Topic :: Scientific/Engineering :: Medical Science Apps.
Classifier: Topic :: Scientific/Engineering :: Mathematics
Classifier: Programming Language :: Python :: 3
Classifier: Programming Language :: Python :: 3.9
Classifier: Programming Language :: Python :: 3.10
Classifier: Programming Language :: Python :: 3.11
Classifier: Programming Language :: Python :: 3.12
Classifier: Operating System :: OS Independent
Requires-Python: >=3.9
License-File: LICENSE
Requires-Dist: numpy>=1.24.0
Requires-Dist: pandas>=2.0.0
Requires-Dist: matplotlib>=3.7.0
Requires-Dist: scipy>=1.10.0
Requires-Dist: statsmodels>=0.14.0
Requires-Dist: scikit-learn>=1.2.0
Requires-Dist: python-box>=7.0.0
Requires-Dist: pytest>=8.4.2
Requires-Dist: pydantic-settings>=2.0.0
Requires-Dist: ipykernel>=6.31.0
Requires-Dist: jupyter>=1.1.1
Requires-Dist: notebook>=7.5.0
Requires-Dist: seaborn>=0.13.2
Requires-Dist: factor-analyzer>=0.5.1
Requires-Dist: pytest-cov>=7.0.0
Requires-Dist: tabulate>=0.9.0
Provides-Extra: dev
Requires-Dist: pytest>=7.0.0; extra == "dev"
Requires-Dist: pytest-cov>=4.0.0; extra == "dev"
Requires-Dist: black>=23.0.0; extra == "dev"
Requires-Dist: flake8>=6.0.0; extra == "dev"
Requires-Dist: mypy>=1.0.0; extra == "dev"
Requires-Dist: pre-commit>=3.0.0; extra == "dev"
Requires-Dist: ipython>=8.0.0; extra == "dev"
Requires-Dist: jupyter>=1.0.0; extra == "dev"
Provides-Extra: docs
Requires-Dist: sphinx>=7.0.0; extra == "docs"
Requires-Dist: sphinx-rtd-theme>=1.3.0; extra == "docs"
Requires-Dist: myst-parser>=2.0.0; extra == "docs"
Requires-Dist: sphinxcontrib-napoleon>=0.7; extra == "docs"
Provides-Extra: test
Requires-Dist: pytest>=7.0.0; extra == "test"
Requires-Dist: pytest-cov>=4.0.0; extra == "test"
Requires-Dist: pytest-xdist>=3.0.0; extra == "test"
Requires-Dist: tox>=4.0.0; extra == "test"
Dynamic: license-file
